elliptec/__init__.py
elliptec/cmd.py
elliptec/controller.py
elliptec/devices.py
elliptec/errcodes.py
elliptec/errors.py
elliptec/iris.py
elliptec/linear.py
elliptec/motor.py
elliptec/rotator.py
elliptec/scan.py
elliptec/shutter.py
elliptec/slider.py
elliptec/tools.py
elliptec-0.0.6.dist-info/METADATA
elliptec-0.0.6.dist-info/WHEEL
elliptec-0.0.6.dist-info/licenses/LICENSE
elliptec-0.0.6.dist-info/RECORD
