Metadata-Version: 2.4
Name: elliptec
Version: 0.0.6
Summary: Simple control of Thorlabs Elliptec devices.
Project-URL: Homepage, https://github.com/roesel/elliptec
Project-URL: Documentation, https://elliptec.readthedocs.io
Project-URL: Bug Tracker, https://github.com/roesel/elliptec/issues
Author-email: David Roesel <roesel@gmail.com>
License:                     GNU GENERAL PUBLIC LICENSE
License-File: LICENSE
Keywords: elliptec,serial,thorlabs
Classifier: License :: OSI Approved :: GNU General Public License v3 (GPLv3)
Classifier: Operating System :: OS Independent
Classifier: Programming Language :: Python :: 3
Requires-Python: >=3.7
Requires-Dist: pyserial
